[{"file": "VL35-G001.html", "title": "Предисловие", "headings": [{"tag": "h1", "text": "Предисловие", "level": 1, "id": null, "filename": "VL35-G001.html"}, {"tag": "h4", "text": "* * *", "level": 4, "id": "h1-2", "filename": "VL35-G001.html"}]}, {"file": "VL35-G002.html", "title": "К гражданам России!", "headings": [{"tag": "h1", "text": "1917 г.", "level": 1, "id": null, "filename": "VL35-G002.html"}, {"tag": "h2", "text": "К гражданам России!  ", "level": 2, "id": "h2-2", "filename": "VL35-G002.html"}]}, {"file": "VL35-G003.html", "title": "Заседание Петроградского Совета рабочих и солдатских депутатов 25 октября(7 ноября) 1917 г.", "headings": [{"tag": "h2", "text": "Заседание Петроградского Совета рабочих и солдатских депутатов 25 октября(7 ноября) 1917 г.  ", "level": 2, "id": "h3-1", "filename": "VL35-G003.html"}, {"tag": "h3", "text": "1. Доклад о задачах власти Советов.  Газетный отчет", "level": 3, "id": "h3-2", "filename": "VL35-G003.html"}]}, {"file": "VL35-G004.html", "title": "2. Резолюция", "headings": [{"tag": "h3", "text": "2. Резолюция", "level": 3, "id": null, "filename": "VL35-G004.html"}]}, {"file": "VL35-G005.html", "title": "Второй Всероссийский съезд Советов рабочих и солдатских депутатов \n25–26 октября (7–8 ноября) 1917 г.", "headings": [{"tag": "h2", "text": "Второй Всероссийский съезд Советов рабочих и солдатских депутатов    25–26 октября (7–8 ноября) 1917 г.", "level": 2, "id": null, "filename": "VL35-G005.html"}]}, {"file": "VL35-G006.html", "title": "1. Рабочим, солдатам и крестьянам!", "headings": [{"tag": "h3", "text": "1. Рабочим, солдатам и крестьянам!", "level": 3, "id": null, "filename": "VL35-G006.html"}]}, {"file": "VL35-G007.html", "title": "2. Доклад о мире 26 октября (8 ноября)", "headings": [{"tag": "h3", "text": "2. Доклад о мире 26 октября (8 ноября)", "level": 3, "id": null, "filename": "VL35-G007.html"}]}, {"file": "VL35-G008.html", "title": "Декрет о мире", "headings": [{"tag": "h4", "text": "Декрет о мире", "level": 4, "id": "h8-1", "filename": "VL35-G008.html"}, {"tag": "h4", "text": "* * *", "level": 4, "id": "h8-2", "filename": "VL35-G008.html"}]}, {"file": "VL35-G009.html", "title": "3. Заключительное слово по докладу о мире 26 октября (8 ноября)", "headings": [{"tag": "h3", "text": "3. Заключительное слово по докладу о мире 26 октября (8 ноября)", "level": 3, "id": null, "filename": "VL35-G009.html"}]}, {"file": "VL35-G010.html", "title": "4. Доклад о земле 26 октября (8 ноября)", "headings": [{"tag": "h3", "text": "4. Доклад о земле 26 октября (8 ноября)", "level": 3, "id": null, "filename": "VL35-G010.html"}]}, {"file": "VL35-G011.html", "title": "Декрет о земле", "headings": [{"tag": "h4", "text": "Декрет о земле", "level": 4, "id": "h11-1", "filename": "VL35-G011.html"}, {"tag": "h4", "text": "* * *", "level": 4, "id": "h11-2", "filename": "VL35-G011.html"}]}, {"file": "VL35-G012.html", "title": "5. Постановление об образовании рабочего и крестьянского правительства", "headings": [{"tag": "h3", "text": "5. Постановление об образовании рабочего и крестьянского правительства", "level": 3, "id": null, "filename": "VL35-G012.html"}]}, {"file": "VL35-G013.html", "title": "Проект положения о рабочем контроле", "headings": [{"tag": "h2", "text": "Проект положения о рабочем контроле  ", "level": 2, "id": null, "filename": "VL35-G013.html"}]}, {"file": "VL35-G014.html", "title": "Разговор с Гельсингфорсом по прямому проводу 27 октября (9 ноября) 1917 г.", "headings": [{"tag": "h2", "text": "Разговор с Гельсингфорсом по прямому проводу 27 октября (9 ноября) 1917 г.", "level": 2, "id": "h14-1", "filename": "VL35-G014.html"}, {"tag": "h3", "text": "1. Разговор с председателем исполкома Гельсингфорсского Совета депутатов армии, флота и рабочих Финляндии А. Л. Шейнманом", "level": 3, "id": "h14-2", "filename": "VL35-G014.html"}]}, {"file": "VL35-G015.html", "title": "2. Разговор с председателем военного отдела областного комитета армии, флота и рабочих Финляндии Михайловым", "headings": [{"tag": "h3", "text": "2. Разговор с председателем военного отдела областного комитета армии, флота и рабочих Финляндии Михайловым", "level": 3, "id": null, "filename": "VL35-G015.html"}]}, {"file": "VL35-G016.html", "title": "3. Разговор с товарищем председателя центробалта Η. Φ. Измайловым", "headings": [{"tag": "h3", "text": "3. Разговор с товарищем председателя центробалта Η. Φ. Измайловым", "level": 3, "id": null, "filename": "VL35-G016.html"}]}, {"file": "VL35-G017.html", "title": "Совещание полковых представителей Петроградского гарнизона 29 октября (11 ноября) 1917 г. Газетный отчет", "headings": [{"tag": "h2", "text": "Совещание полковых представителей Петроградского гарнизона 29 октября (11 ноября) 1917 г.    Газетный отчет", "level": 2, "id": "h17-1", "filename": "VL35-G017.html"}, {"tag": "h3", "text": "1. Доклад о текущем моменте", "level": 3, "id": "h17-2", "filename": "VL35-G017.html"}]}, {"file": "VL35-G018.html", "title": "2. Выступление по вопросу о вооружении частей", "headings": [{"tag": "h3", "text": "2. Выступление по вопросу о вооружении частей", "level": 3, "id": null, "filename": "VL35-G018.html"}]}, {"file": "VL35-G019.html", "title": "3. Выступление по вопросу о водворении порядка в городе", "headings": [{"tag": "h3", "text": "3. Выступление по вопросу о водворении порядка в городе", "level": 3, "id": null, "filename": "VL35-G019.html"}]}, {"file": "VL35-G020.html", "title": "Радио Совета народных комиссаров 30 октября (12 ноября) 1917 г.", "headings": [{"tag": "h2", "text": "Радио Совета народных комиссаров 30 октября (12 ноября) 1917 г.", "level": 2, "id": null, "filename": "VL35-G020.html"}]}, {"file": "VL35-G021.html", "title": "Набросок правил для служащих", "headings": [{"tag": "h2", "text": "Набросок правил для служащих", "level": 2, "id": null, "filename": "VL35-G021.html"}]}, {"file": "VL35-G022.html", "title": "Выступления на заседании ЦК РСДРП(б) 1 (14) ноября 1917 г. Протокольная запись", "headings": [{"tag": "h2", "text": "Выступления на заседании ЦК РСДРП(б) 1 (14) ноября 1917 г.  Протокольная запись  ", "level": 2, "id": "h22-1", "filename": "VL35-G022.html"}, {"tag": "h3", "text": "1", "level": 3, "id": "h22-2", "filename": "VL35-G022.html"}]}, {"file": "VL35-G023.html", "title": "2", "headings": [{"tag": "h3", "text": "2", "level": 3, "id": null, "filename": "VL35-G023.html"}]}, {"file": "VL35-G024.html", "title": "3", "headings": [{"tag": "h3", "text": "3", "level": 3, "id": null, "filename": "VL35-G024.html"}]}, {"file": "VL35-G025.html", "title": "Резолюция ЦК РСДРП(б) по вопросу об оппозиции внутри ЦК 2 (15) ноября 1917 г.", "headings": [{"tag": "h2", "text": "Резолюция ЦК РСДРП(б) по вопросу об оппозиции внутри ЦК 2 (15) ноября 1917 г.  ", "level": 2, "id": null, "filename": "VL35-G025.html"}]}, {"file": "VL35-G026.html", "title": "Ультиматум большинства ЦК РСДРП(б) меньшинству", "headings": [{"tag": "h2", "text": "Ультиматум большинства ЦК РСДРП(б) меньшинству  ", "level": 2, "id": null, "filename": "VL35-G026.html"}]}, {"file": "VL35-G027.html", "title": "Выступление на заседании СНК 3 (16) ноября 1917 г.", "headings": [{"tag": "h2", "text": "Выступление на заседании СНК 3 (16) ноября 1917 г.", "level": 2, "id": null, "filename": "VL35-G027.html"}]}, {"file": "VL35-G028.html", "title": "Проект резолюции о свободе печати", "headings": [{"tag": "h2", "text": "Проект резолюции о свободе печати  ", "level": 2, "id": null, "filename": "VL35-G028.html"}]}, {"file": "VL35-G029.html", "title": "Заседание ВЦИК 4 (17) ноября 1917 г.", "headings": [{"tag": "h2", "text": "Заседание ВЦИК 4 (17) ноября 1917 г.", "level": 2, "id": "h29-1", "filename": "VL35-G029.html"}, {"tag": "h3", "text": "1. Речь по вопросу о печати", "level": 3, "id": "h29-2", "filename": "VL35-G029.html"}]}, {"file": "VL35-G030.html", "title": "2. Ответ на запрос левых эсеров", "headings": [{"tag": "h3", "text": "2. Ответ на запрос левых эсеров", "level": 3, "id": null, "filename": "VL35-G030.html"}]}, {"file": "VL35-G031.html", "title": "3. Выступления по запросу левых эсеров", "headings": [{"tag": "h3", "text": "3. Выступления по запросу левых эсеров", "level": 3, "id": "h31-1", "filename": "VL35-G031.html"}, {"tag": "h4", "text": "1", "level": 4, "id": "h31-2", "filename": "VL35-G031.html"}]}, {"file": "VL35-G032.html", "title": "2", "headings": [{"tag": "h4", "text": "2", "level": 4, "id": null, "filename": "VL35-G032.html"}]}, {"file": "VL35-G033.html", "title": "4. Речь и резолюция по поводу заявления группы народных комиссаров об уходе из совнаркома", "headings": [{"tag": "h3", "text": "4. Речь и резолюция по поводу заявления группы народных комиссаров об уходе из совнаркома", "level": 3, "id": null, "filename": "VL35-G033.html"}]}, {"file": "VL35-G034.html", "title": "Речь на заседании Петроградского Совета рабочих и солдатских депутатов совместно с фронтовыми представителями 4 (17) ноября 1917 г. \nГазетный отчет", "headings": [{"tag": "h2", "text": "Речь на заседании Петроградского Совета рабочих и солдатских депутатов совместно с фронтовыми представителями 4 (17) ноября 1917 г.  Газетный отчет", "level": 2, "id": null, "filename": "VL35-G034.html"}]}, {"file": "VL35-G035.html", "title": "К населению", "headings": [{"tag": "h2", "text": "К населению", "level": 2, "id": null, "filename": "VL35-G035.html"}]}, {"file": "VL35-G036.html", "title": "Ответ на запросы крестьян", "headings": [{"tag": "h2", "text": "Ответ на запросы крестьян  ", "level": 2, "id": null, "filename": "VL35-G036.html"}]}, {"file": "VL35-G037.html", "title": "От Центрального Комитета российской социал-демократической рабочей партии (большевиков)", "headings": [{"tag": "h2", "text": "От Центрального Комитета российской социал-демократической рабочей партии (большевиков)", "level": 2, "id": null, "filename": "VL35-G037.html"}]}, {"file": "VL35-G038.html", "title": "От Центрального Комитета российской социал-демократической рабочей партии (большевиков). Ко всем членам партии и ко всем трудящимся классам России", "headings": [{"tag": "h2", "text": "От Центрального Комитета российской социал-демократической рабочей партии (большевиков).  Ко всем членам партии и ко всем трудящимся классам России", "level": 2, "id": "h38-1", "filename": "VL35-G038.html"}, {"tag": "h4", "text": "* * *", "level": 4, "id": "h38-2", "filename": "VL35-G038.html"}]}, {"file": "VL35-G039.html", "title": "Разговор правительства со ставкой по прямому проводу 9 (22) ноября 1917 г.", "headings": [{"tag": "h2", "text": "Разговор правительства со ставкой по прямому проводу 9 (22) ноября 1917 г.  ", "level": 2, "id": null, "filename": "VL35-G039.html"}]}, {"file": "VL35-G040.html", "title": "Радио всем. \nВсем полковым, дивизионным, корпусным, армейским и другим комитетам, всем солдатам революционной армии и матросам революционного флота", "headings": [{"tag": "h2", "text": "Радио всем.  Всем полковым, дивизионным, корпусным, армейским и другим комитетам, всем солдатам революционной армии и матросам революционного флота  ", "level": 2, "id": null, "filename": "VL35-G040.html"}]}, {"file": "VL35-G041.html", "title": "Предисловие к брошюре «Как обманули народ социалисты-революционеры и что дало народу новое правительство большевиков»", "headings": [{"tag": "h2", "text": "Предисловие к брошюре «Как обманули народ социалисты-революционеры и что дало народу новое правительство большевиков»", "level": 2, "id": null, "filename": "VL35-G041.html"}]}, {"file": "VL35-G042.html", "title": "Заседание ВЦИК 10 (23) ноября 1917 г.", "headings": [{"tag": "h2", "text": "Заседание ВЦИК 10 (23) ноября 1917 г.", "level": 2, "id": "h42-1", "filename": "VL35-G042.html"}, {"tag": "h3", "text": "1. Доклад о переговорах с Духониным", "level": 3, "id": "h42-2", "filename": "VL35-G042.html"}]}, {"file": "VL35-G043.html", "title": "2. Заключительное слово", "headings": [{"tag": "h3", "text": "2. Заключительное слово", "level": 3, "id": null, "filename": "VL35-G043.html"}]}, {"file": "VL35-G044.html", "title": "Совет народных комиссаров военно-революционному комитету", "headings": [{"tag": "h2", "text": "Совет народных комиссаров военно-революционному комитету", "level": 2, "id": null, "filename": "VL35-G044.html"}]}, {"file": "VL35-G045.html", "title": "Письмо финским товарищам \nМаннеру, Сироле, Куусинену, Валпасу, Вийку", "headings": [{"tag": "h2", "text": "Письмо финским товарищам  Маннеру, Сироле, Куусинену, Валпасу, Вийку", "level": 2, "id": null, "filename": "VL35-G045.html"}]}, {"file": "VL35-G046.html", "title": "Чрезвычайный Всероссийский съезд Советов крестьянских депутатов 10–25 ноября (23 ноября – 8 декабря) 1917 г.", "headings": [{"tag": "h2", "text": "Чрезвычайный Всероссийский съезд Советов крестьянских депутатов    10–25 ноября (23 ноября – 8 декабря) 1917 г.", "level": 2, "id": null, "filename": "VL35-G046.html"}]}, {"file": "VL35-G047.html", "title": "1. Заявление во фракцию большевиков чрезвычайного Всероссийского съезда Советов крестьянских депутатов", "headings": [{"tag": "h3", "text": "1. Заявление во фракцию большевиков чрезвычайного Всероссийского съезда Советов крестьянских депутатов  ", "level": 3, "id": null, "filename": "VL35-G047.html"}]}, {"file": "VL35-G048.html", "title": "2. Речь по аграрному вопросу 14 (27) ноября. \nГазетный отчет", "headings": [{"tag": "h3", "text": "2. Речь по аграрному вопросу 14 (27) ноября.  Газетный отчет", "level": 3, "id": null, "filename": "VL35-G048.html"}]}, {"file": "VL35-G049.html", "title": "3. Проект резолюции", "headings": [{"tag": "h3", "text": "3. Проект резолюции", "level": 3, "id": null, "filename": "VL35-G049.html"}]}, {"file": "VL35-G050.html", "title": "4. Речь по поводу заявления представителя Викжеля 18 ноября (1 декабря). \nГазетный отчет", "headings": [{"tag": "h3", "text": "4. Речь по поводу заявления представителя Викжеля 18 ноября (1 декабря).  Газетный отчет", "level": 3, "id": null, "filename": "VL35-G050.html"}]}, {"file": "VL35-G051.html", "title": "5. Заключительное слово по аграрному вопросу 18 ноября (1 декабря). Газетный отчет", "headings": [{"tag": "h3", "text": "5. Заключительное слово по аграрному вопросу 18 ноября (1 декабря).  Газетный отчет", "level": 3, "id": null, "filename": "VL35-G051.html"}]}, {"file": "VL35-G052.html", "title": "Союз рабочих с трудящимися и эксплуатируемыми крестьянами. \nПисьмо в редакцию «Правды»", "headings": [{"tag": "h2", "text": "Союз рабочих с трудящимися и эксплуатируемыми крестьянами.  Письмо в редакцию «Правды»", "level": 2, "id": null, "filename": "VL35-G052.html"}]}, {"file": "VL35-G053.html", "title": "Об окладах высшим служащим и чиновникам. Проект постановления СНК", "headings": [{"tag": "h2", "text": "Об окладах высшим служащим и чиновникам.  Проект постановления СНК  ", "level": 2, "id": null, "filename": "VL35-G053.html"}]}, {"file": "VL35-G054.html", "title": "Проект декрета о праве отзыва", "headings": [{"tag": "h2", "text": "Проект декрета о праве отзыва  ", "level": 2, "id": null, "filename": "VL35-G054.html"}]}, {"file": "VL35-G055.html", "title": "Тезисы закона о конфискации домов с сдаваемыми в наем квартирами", "headings": [{"tag": "h2", "text": "Тезисы закона о конфискации домов с сдаваемыми в наем квартирами  ", "level": 2, "id": null, "filename": "VL35-G055.html"}]}, {"file": "VL35-G056.html", "title": "Доклад о праве отзыва на заседании ВЦИК 21 ноября (4 декабря) 1917 г.", "headings": [{"tag": "h2", "text": "Доклад о праве отзыва на заседании ВЦИК 21 ноября (4 декабря) 1917 г.", "level": 2, "id": null, "filename": "VL35-G056.html"}]}, {"file": "VL35-G057.html", "title": "Речь на Первом Всероссийском съезде военного флота 22 ноября (5 декабря) 1917 г. Протокольная запись", "headings": [{"tag": "h2", "text": "Речь на Первом Всероссийском съезде военного флота 22 ноября (5 декабря) 1917 г.    Протокольная запись", "level": 2, "id": null, "filename": "VL35-G057.html"}]}, {"file": "VL35-G058.html", "title": "Предисловие к брошюре «Материалы по аграрному вопросу»", "headings": [{"tag": "h2", "text": "Предисловие к брошюре «Материалы по аграрному вопросу»", "level": 2, "id": null, "filename": "VL35-G058.html"}]}, {"file": "VL35-G059.html", "title": "Конспект программы переговоров о мире", "headings": [{"tag": "h2", "text": "Конспект программы переговоров о мире  ", "level": 2, "id": null, "filename": "VL35-G059.html"}]}, {"file": "VL35-G060.html", "title": "Вопросы экономической политики", "headings": [{"tag": "h2", "text": "Вопросы экономической политики  ", "level": 2, "id": null, "filename": "VL35-G060.html"}]}, {"file": "VL35-G061.html", "title": "Набросок программы экономических мероприятий", "headings": [{"tag": "h2", "text": "Набросок программы экономических мероприятий", "level": 2, "id": null, "filename": "VL35-G061.html"}]}, {"file": "VL35-G062.html", "title": "К лозунгам демонстрации", "headings": [{"tag": "h2", "text": "К лозунгам демонстрации  ", "level": 2, "id": null, "filename": "VL35-G062.html"}]}, {"file": "VL35-G063.html", "title": "Декрет об аресте вождей гражданской войны против революции", "headings": [{"tag": "h2", "text": "Декрет об аресте вождей гражданской войны против революции  ", "level": 2, "id": null, "filename": "VL35-G063.html"}]}, {"file": "VL35-G064.html", "title": "Об ответственности за голословные обвинения. \nПроект постановления ЦК РСДРП(б)", "headings": [{"tag": "h2", "text": "Об ответственности за голословные обвинения.  Проект постановления ЦК РСДРП  (б)  ", "level": 2, "id": null, "filename": "VL35-G064.html"}]}, {"file": "VL35-G065.html", "title": "Выступления на заседании ЦК РСДРП(б) 29 ноября (12 декабря) 1917 г. Протокольная запись", "headings": [{"tag": "h2", "text": "Выступления на заседании ЦК РСДРП(б) 29 ноября (12 декабря) 1917 г.  Протокольная запись", "level": 2, "id": "h65-1", "filename": "VL35-G065.html"}, {"tag": "h3", "text": "1", "level": 3, "id": "h65-2", "filename": "VL35-G065.html"}]}, {"file": "VL35-G066.html", "title": "2", "headings": [{"tag": "h3", "text": "2", "level": 3, "id": null, "filename": "VL35-G066.html"}]}, {"file": "VL35-G067.html", "title": "3", "headings": [{"tag": "h3", "text": "3", "level": 3, "id": null, "filename": "VL35-G067.html"}]}, {"file": "VL35-G068.html", "title": "О переводе военных заводов на хозяйственно-полезные работы. Постановление Совета Народных Комиссаров", "headings": [{"tag": "h2", "text": "О переводе военных заводов на хозяйственно-полезные работы.  Постановление Совета Народных Комиссаров", "level": 2, "id": null, "filename": "VL35-G068.html"}]}, {"file": "VL35-G069.html", "title": "О задачах публичной библиотеки в Петрограде", "headings": [{"tag": "h2", "text": "О задачах публичной библиотеки в Петрограде", "level": 2, "id": null, "filename": "VL35-G069.html"}]}, {"file": "VL35-G070.html", "title": "Заседание ВЦИК 1 (14) декабря 1917 г.", "headings": [{"tag": "h2", "text": "Заседание ВЦИК 1 (14) декабря 1917 г.", "level": 2, "id": "h70-1", "filename": "VL35-G070.html"}, {"tag": "h3", "text": "1. Выступление по вопросу о создании Высшего Совета народного хозяйства    .  Газетный отчет", "level": 3, "id": "h70-2", "filename": "VL35-G070.html"}]}, {"file": "VL35-G071.html", "title": "2. Речь по вопросу об Учредительном собрании", "headings": [{"tag": "h3", "text": "2. Речь по вопросу об Учредительном собрании  ", "level": 3, "id": null, "filename": "VL35-G071.html"}]}, {"file": "VL35-G072.html", "title": "3. Резолюция о декрете по поводу кадетской партии", "headings": [{"tag": "h3", "text": "3. Резолюция о декрете по поводу кадетской партии", "level": 3, "id": null, "filename": "VL35-G072.html"}]}, {"file": "VL35-G073.html", "title": "Речь на Втором Всероссийском съезде Советов крестьянских депутатов 2 (15) декабря 1917 г.", "headings": [{"tag": "h2", "text": "Речь на Втором Всероссийском съезде Советов крестьянских депутатов 2 (15) декабря 1917 г.  ", "level": 2, "id": null, "filename": "VL35-G073.html"}]}, {"file": "VL35-G074.html", "title": "Манифест к украинскому народу с ультимативными требованиями к Украинской раде", "headings": [{"tag": "h2", "text": "Манифест к украинскому народу с ультимативными требованиями к Украинской раде  ", "level": 2, "id": null, "filename": "VL35-G074.html"}]}, {"file": "VL35-G075.html", "title": "Доклад об экономическом положении рабочих Петрограда и задачах рабочего класса на заседании рабочей секции Петроградского Совета рабочих и солдатских депутатов 4 (17) декабря 1917 г. \nГазетный отчет", "headings": [{"tag": "h2", "text": "Доклад об экономическом положении рабочих Петрограда и задачах рабочего класса на заседании рабочей секции Петроградского Совета рабочих и солдатских депутатов 4 (17) декабря 1917 г.  Газетный отчет", "level": 2, "id": null, "filename": "VL35-G075.html"}]}, {"file": "VL35-G076.html", "title": "Об открытии Учредительного собрания", "headings": [{"tag": "h2", "text": "Об открытии Учредительного собрания", "level": 2, "id": null, "filename": "VL35-G076.html"}]}, {"file": "VL35-G077.html", "title": "Проект воззвания Второго Всероссийского съезда Советов крестьянских депутатов к крестьянству", "headings": [{"tag": "h2", "text": "Проект воззвания Второго Всероссийского съезда Советов крестьянских депутатов к крестьянству  ", "level": 2, "id": null, "filename": "VL35-G077.html"}]}, {"file": "VL35-G078.html", "title": "Записка Ф. Э. Дзержинскому с проектом декрета о борьбе с контрреволюционерами и саботажниками", "headings": [{"tag": "h2", "text": "Записка Ф. Э. Дзержинскому с проектом декрета о борьбе с контрреволюционерами и саботажниками  ", "level": 2, "id": null, "filename": "VL35-G078.html"}]}, {"file": "VL35-G079.html", "title": "Ответы на вопросы, заданные делегацией рабочих Александро-Грушевского района", "headings": [{"tag": "h2", "text": "Ответы на вопросы, заданные делегацией рабочих Александро-Грушевского района  ", "level": 2, "id": null, "filename": "VL35-G079.html"}]}, {"file": "VL35-G080.html", "title": "Речь на заседании ЦК РСДРП(б) 11 (24) декабря 1917 г. \nПротокольная запись", "headings": [{"tag": "h2", "text": "Речь на заседании ЦК РСДРП(б) 11 (24) декабря 1917 г.    Протокольная запись", "level": 2, "id": null, "filename": "VL35-G080.html"}]}, {"file": "VL35-G081.html", "title": "Проект резолюции о временном бюро фракции большевиков в Учредительном собрании", "headings": [{"tag": "h2", "text": "Проект резолюции о временном бюро фракции большевиков в Учредительном собрании", "level": 2, "id": null, "filename": "VL35-G081.html"}]}, {"file": "VL35-G082.html", "title": "Тезисы об Учредительном собрании", "headings": [{"tag": "h2", "text": "Тезисы об Учредительном собрании", "level": 2, "id": null, "filename": "VL35-G082.html"}]}, {"file": "VL35-G083.html", "title": "Речь на Чрезвычайном Всероссийском съезде железнодорожных рабочих и мастеровых 13 (26) декабря 1917 г.", "headings": [{"tag": "h2", "text": "Речь на Чрезвычайном Всероссийском съезде железнодорожных рабочих и мастеровых 13 (26) декабря 1917 г.  ", "level": 2, "id": null, "filename": "VL35-G083.html"}]}, {"file": "VL35-G084.html", "title": "За хлеб и за мир", "headings": [{"tag": "h2", "text": "За хлеб и за мир  ", "level": 2, "id": null, "filename": "VL35-G084.html"}]}, {"file": "VL35-G085.html", "title": "Речь о национализации банков на заседании ВЦИК 14 (27) декабря 1917 г. Протокольная запись", "headings": [{"tag": "h2", "text": "Речь о национализации банков на заседании ВЦИК 14 (27) декабря 1917 г.    Протокольная запись", "level": 2, "id": null, "filename": "VL35-G085.html"}]}, {"file": "VL35-G086.html", "title": "Проект декрета о проведении в жизнь национализации банков и о необходимых в связи с этим мерах", "headings": [{"tag": "h2", "text": "Проект декрета о проведении в жизнь национализации банков и о необходимых в связи с этим мерах  ", "level": 2, "id": null, "filename": "VL35-G086.html"}]}, {"file": "VL35-G087.html", "title": "Об организации комиссии практиков. \nПроект постановления СНК", "headings": [{"tag": "h2", "text": "Об организации комиссии практиков.  Проект постановления СНК  ", "level": 2, "id": null, "filename": "VL35-G087.html"}]}, {"file": "VL35-G088.html", "title": "Вопросы делегатам общеармейского съезда по демобилизации армии", "headings": [{"tag": "h2", "text": "Вопросы делегатам общеармейского съезда по демобилизации армии  ", "level": 2, "id": null, "filename": "VL35-G088.html"}]}, {"file": "VL35-G089.html", "title": "Проект резолюции Совета Народных Комиссаров", "headings": [{"tag": "h2", "text": "Проект резолюции Совета Народных Комиссаров  ", "level": 2, "id": null, "filename": "VL35-G089.html"}]}, {"file": "VL35-G090.html", "title": "Резолюция Совета Народных Комиссаров о переговорах с Радой", "headings": [{"tag": "h2", "text": "Резолюция Совета Народных Комиссаров о переговорах с Радой", "level": 2, "id": null, "filename": "VL35-G090.html"}]}, {"file": "VL35-G091.html", "title": "Плеханов о терроре", "headings": [{"tag": "h2", "text": "Плеханов о терроре", "level": 2, "id": null, "filename": "VL35-G091.html"}]}, {"file": "VL35-G092.html", "title": "Из дневника публициста \n(Темы для разработки)", "headings": [{"tag": "h2", "text": "Из дневника публициста  (Темы для разработки)  ", "level": 2, "id": null, "filename": "VL35-G092.html"}]}, {"file": "VL35-G093.html", "title": "Запуганные крахом старого и борющиеся за новое", "headings": [{"tag": "h2", "text": "Запуганные крахом старого и борющиеся за новое", "level": 2, "id": null, "filename": "VL35-G093.html"}]}, {"file": "VL35-G094.html", "title": "Как организовать соревнование?", "headings": [{"tag": "h2", "text": "Как организовать соревнование?", "level": 2, "id": null, "filename": "VL35-G094.html"}]}, {"file": "VL35-G095.html", "title": "Проект декрета о потребительных коммунах", "headings": [{"tag": "h2", "text": "Проект декрета о потребительных коммунах  ", "level": 2, "id": "h95-1", "filename": "VL35-G095.html"}, {"tag": "h3", "text": "1. Предварительные тезисы", "level": 3, "id": "h95-2", "filename": "VL35-G095.html"}]}, {"file": "VL35-G096.html", "title": "2. Проект декрета", "headings": [{"tag": "h3", "text": "2. Проект декрета", "level": 3, "id": null, "filename": "VL35-G096.html"}]}, {"file": "VL35-G097.html", "title": "Постановление СНК об ответе Рады Совету Народных Комиссаров", "headings": [{"tag": "h2", "text": "Постановление СНК об ответе Рады Совету Народных Комиссаров", "level": 2, "id": null, "filename": "VL35-G097.html"}]}, {"file": "VL35-G098.html", "title": "Проект резолюции ЦК РСДРП(б) об исключении С. А. Лозовского из партии", "headings": [{"tag": "h2", "text": "Проект резолюции ЦК РСДРП(б) об исключении С. А. Лозовского из партии", "level": 2, "id": null, "filename": "VL35-G098.html"}]}, {"file": "VL35-G099.html", "title": "Постановление СНК о борьбе против Каледина", "headings": [{"tag": "h2", "text": "Постановление СНК о борьбе против Каледина", "level": 2, "id": "h99-1", "filename": "VL35-G099.html"}, {"tag": "h3", "text": "1. Постановление СНК", "level": 3, "id": "h99-2", "filename": "VL35-G099.html"}]}, {"file": "VL35-G100.html", "title": "2. Дополнение к постановлению СНК", "headings": [{"tag": "h3", "text": "2. Дополнение к постановлению СНК", "level": 3, "id": null, "filename": "VL35-G100.html"}]}, {"file": "VL35-G101.html", "title": "Речь на проводах первых эшелонов социалистической армии 1 (14) января 1918 г. \nКраткий газетный отчет", "headings": [{"tag": "h1", "text": "1918 г.", "level": 1, "id": null, "filename": "VL35-G101.html"}, {"tag": "h2", "text": "Речь на проводах первых эшелонов социалистической армии 1 (14) января 1918 г.    Краткий газетный отчет", "level": 2, "id": "h101-2", "filename": "VL35-G101.html"}]}, {"file": "VL35-G102.html", "title": "О норме оплаты высших должностных лиц. \nПроект постановления СНК", "headings": [{"tag": "h2", "text": "О норме оплаты высших должностных лиц.  Проект постановления СНК  ", "level": 2, "id": null, "filename": "VL35-G102.html"}]}, {"file": "VL35-G103.html", "title": "Декларация прав трудящегося и эксплуатируемого народа", "headings": [{"tag": "h2", "text": "Декларация прав трудящегося и эксплуатируемого народа  ", "level": 2, "id": null, "filename": "VL35-G103.html"}]}, {"file": "VL35-G104.html", "title": "Общеармейскому съезду по демобилизации армии", "headings": [{"tag": "h2", "text": "Общеармейскому съезду по демобилизации армии", "level": 2, "id": null, "filename": "VL35-G104.html"}]}, {"file": "VL35-G105.html", "title": "Разговор с председателем советской мирной делегации в Брест-Литовске Л. Д. Троцким по прямому проводу 3 (16) января 1918 г.", "headings": [{"tag": "h2", "text": "Разговор с председателем советской мирной делегации в Брест-Литовске Л. Д. Троцким по прямому проводу 3 (16) января 1918 г.", "level": 2, "id": "h105-1", "filename": "VL35-G105.html"}, {"tag": "h3", "text": "1", "level": 3, "id": "h105-2", "filename": "VL35-G105.html"}]}, {"file": "VL35-G106.html", "title": "2", "headings": [{"tag": "h3", "text": "2", "level": 3, "id": null, "filename": "VL35-G106.html"}]}, {"file": "VL35-G107.html", "title": "3", "headings": [{"tag": "h3", "text": "3", "level": 3, "id": null, "filename": "VL35-G107.html"}]}, {"file": "VL35-G108.html", "title": "4", "headings": [{"tag": "h3", "text": "4", "level": 3, "id": null, "filename": "VL35-G108.html"}]}, {"file": "VL35-G109.html", "title": "Постановление ВЦИК 3 (16) января 1918 г.", "headings": [{"tag": "h2", "text": "Постановление ВЦИК 3 (16) января 1918 г.", "level": 2, "id": null, "filename": "VL35-G109.html"}]}, {"file": "VL35-G110.html", "title": "Декларация фракции РСДРП (большевиков), оглашенная на заседании Учредительного собрания 5 (18) января 1918 г.", "headings": [{"tag": "h2", "text": "Декларация фракции РСДРП (большевиков), оглашенная на заседании Учредительного собрания 5 (18) января 1918 г.  ", "level": 2, "id": null, "filename": "VL35-G110.html"}]}, {"file": "VL35-G111.html", "title": "Люди с того света", "headings": [{"tag": "h2", "text": "Люди с того света", "level": 2, "id": null, "filename": "VL35-G111.html"}]}, {"file": "VL35-G112.html", "title": "Проект Декрета о роспуске Учредительного собрания", "headings": [{"tag": "h2", "text": "Проект Декрета о роспуске Учредительного собрания  ", "level": 2, "id": "h112-1", "filename": "VL35-G112.html"}, {"tag": "h3", "text": "1. Тезисы", "level": 3, "id": "h112-2", "filename": "VL35-G112.html"}]}, {"file": "VL35-G113.html", "title": "2. Проект декрета", "headings": [{"tag": "h3", "text": "2. Проект декрета", "level": 3, "id": null, "filename": "VL35-G113.html"}]}, {"file": "VL35-G114.html", "title": "Речь о роспуске Учредительного собрания на заседании ВЦИК 6 (19) января 1918 г.", "headings": [{"tag": "h2", "text": "Речь о роспуске Учредительного собрания на заседании ВЦИК 6 (19) января 1918 г.", "level": 2, "id": null, "filename": "VL35-G114.html"}]}, {"file": "VL35-G115.html", "title": "К истории вопроса о несчастном мире", "headings": [{"tag": "h2", "text": "К истории вопроса о несчастном мире", "level": 2, "id": null, "filename": "VL35-G115.html"}]}, {"file": "VL35-G116.html", "title": "Тезисы по вопросу о немедленном заключении сепаратного и аннексионистского мира", "headings": [{"tag": "h3", "text": "Тезисы по вопросу о немедленном заключении сепаратного и аннексионистского мира  ", "level": 3, "id": null, "filename": "VL35-G116.html"}]}, {"file": "VL35-G117.html", "title": "Послесловие к тезисам по вопросу о немедленном заключении сепаратного и аннексионистского мира", "headings": [{"tag": "h2", "text": "Послесловие к тезисам по вопросу о немедленном заключении сепаратного и аннексионистского мира", "level": 2, "id": null, "filename": "VL35-G117.html"}]}, {"file": "VL35-G118.html", "title": "Речи о войне и мире на заседании ЦК РСДРП(б) 11 (24) января 1918 г. Протокольная запись", "headings": [{"tag": "h2", "text": "Речи о войне и мире на заседании ЦК РСДРП(б) 11 (24) января 1918 г.    Протокольная запись", "level": 2, "id": "h118-1", "filename": "VL35-G118.html"}, {"tag": "h3", "text": "1", "level": 3, "id": "h118-2", "filename": "VL35-G118.html"}]}, {"file": "VL35-G119.html", "title": "2", "headings": [{"tag": "h3", "text": "2", "level": 3, "id": null, "filename": "VL35-G119.html"}]}, {"file": "VL35-G120.html", "title": "3", "headings": [{"tag": "h3", "text": "3", "level": 3, "id": null, "filename": "VL35-G120.html"}]}, {"file": "VL35-G121.html", "title": "Третий Всероссийский съезд Советов рабочих, солдатских и крестьянских депутатов. 10–18 (23–31) января 1918 г.", "headings": [{"tag": "h2", "text": "Третий Всероссийский съезд Советов рабочих, солдатских и крестьянских депутатов    .  10–18 (23–31) января 1918 г.", "level": 2, "id": null, "filename": "VL35-G121.html"}]}, {"file": "VL35-G122.html", "title": "1. Доклад о деятельности Совета Народных Комиссаров 11 (24) января", "headings": [{"tag": "h3", "text": "1. Доклад о деятельности Совета Народных Комиссаров 11 (24) января", "level": 3, "id": null, "filename": "VL35-G122.html"}]}, {"file": "VL35-G123.html", "title": "2. Заключительное слово по докладу Совета Народных Комиссаров \n12 (25) января", "headings": [{"tag": "h3", "text": "2. Заключительное слово по докладу Совета Народных Комиссаров  12 (25) января", "level": 3, "id": null, "filename": "VL35-G123.html"}]}, {"file": "VL35-G124.html", "title": "3. Проект Декрета об устранении в советском законодательстве ссылок на Учредительное собрание", "headings": [{"tag": "h3", "text": "3. Проект Декрета об устранении в советском законодательстве ссылок на Учредительное собрание  ", "level": 3, "id": null, "filename": "VL35-G124.html"}]}, {"file": "VL35-G125.html", "title": "4. Заключительное слово перед закрытием съезда 18 (31) января", "headings": [{"tag": "h3", "text": "4. Заключительное слово перед закрытием съезда 18 (31) января", "level": 3, "id": null, "filename": "VL35-G125.html"}]}, {"file": "VL35-G126.html", "title": "Предписание штабу Красной гвардии", "headings": [{"tag": "h2", "text": "Предписание штабу Красной гвардии", "level": 2, "id": null, "filename": "VL35-G126.html"}]}, {"file": "VL35-G127.html", "title": "Чрезвычайный Всероссийский железнодорожный съезд 5–30 января (18 января – 12 февраля) 1918 г.", "headings": [{"tag": "h2", "text": "Чрезвычайный Всероссийский железнодорожный съезд    5–30 января (18 января – 12 февраля) 1918 г.", "level": 2, "id": "h127-1", "filename": "VL35-G127.html"}, {"tag": "h3", "text": "1. Доклад Совета Народных Комиссаров 13 (26) января", "level": 3, "id": "h127-2", "filename": "VL35-G127.html"}]}, {"file": "VL35-G128.html", "title": "2. Ответы на записки", "headings": [{"tag": "h3", "text": "2. Ответы на записки", "level": 3, "id": null, "filename": "VL35-G128.html"}]}, {"file": "VL35-G129.html", "title": "Совещание президиума Петроградского Совета с представителями продовольственных организаций \n14 (27) января 1918 г.", "headings": [{"tag": "h2", "text": "Совещание президиума Петроградского Совета с представителями продовольственных организаций  14 (27) января 1918 г.  ", "level": 2, "id": "h129-1", "filename": "VL35-G129.html"}, {"tag": "h3", "text": "1. Выступления по вопросу о мерах борьбы с голодом", "level": 3, "id": "h129-2", "filename": "VL35-G129.html"}, {"tag": "h4", "text": "1", "level": 4, "id": "h129-3", "filename": "VL35-G129.html"}]}, {"file": "VL35-G130.html", "title": "2", "headings": [{"tag": "h4", "text": "2", "level": 4, "id": null, "filename": "VL35-G130.html"}]}, {"file": "VL35-G131.html", "title": "2. Проект резолюции", "headings": [{"tag": "h3", "text": "2. Проект резолюции", "level": 3, "id": null, "filename": "VL35-G131.html"}]}, {"file": "VL35-G132.html", "title": "О мерах по улучшению продовольственного положения. Проект постановления СНК", "headings": [{"tag": "h2", "text": "О мерах по улучшению продовольственного положения.  Проект постановления СНК  ", "level": 2, "id": null, "filename": "VL35-G132.html"}]}, {"file": "VL35-G133.html", "title": "О заработной плате. Проект постановления СНК", "headings": [{"tag": "h2", "text": "О заработной плате.  Проект постановления СНК  ", "level": 2, "id": null, "filename": "VL35-G133.html"}]}, {"file": "VL35-G134.html", "title": "Проект Декрета о национализации морского И речного торгового флота", "headings": [{"tag": "h2", "text": "Проект Декрета о национализации морского И речного торгового флота  ", "level": 2, "id": "h134-1", "filename": "VL35-G134.html"}, {"tag": "h3", "text": "1. Проект Декрета", "level": 3, "id": "h134-2", "filename": "VL35-G134.html"}]}, {"file": "VL35-G135.html", "title": "2. Добавление к проекту", "headings": [{"tag": "h3", "text": "2. Добавление к проекту", "level": 3, "id": null, "filename": "VL35-G135.html"}]}, {"file": "VL35-G136.html", "title": "Выступления на заседании ЦК РСДРП(б) 19 января (1 февраля) 1918 г. Протокольная запись", "headings": [{"tag": "h2", "text": "Выступления на заседании ЦК РСДРП(б) 19 января (1 февраля) 1918 г.  Протокольная запись", "level": 2, "id": "h136-1", "filename": "VL35-G136.html"}, {"tag": "h3", "text": "1", "level": 3, "id": "h136-2", "filename": "VL35-G136.html"}]}, {"file": "VL35-G137.html", "title": "2", "headings": [{"tag": "h3", "text": "2", "level": 3, "id": null, "filename": "VL35-G137.html"}]}, {"file": "VL35-G138.html", "title": "3", "headings": [{"tag": "h3", "text": "3", "level": 3, "id": null, "filename": "VL35-G138.html"}]}, {"file": "VL35-G139.html", "title": "4", "headings": [{"tag": "h3", "text": "4", "level": 3, "id": null, "filename": "VL35-G139.html"}]}, {"file": "VL35-G140.html", "title": "5", "headings": [{"tag": "h3", "text": "5", "level": 3, "id": null, "filename": "VL35-G140.html"}]}, {"file": "VL35-G141.html", "title": "6", "headings": [{"tag": "h3", "text": "6", "level": 3, "id": null, "filename": "VL35-G141.html"}]}, {"file": "VL35-G142.html", "title": "По радио всем. Мирной делегации в Брест-Литовске особенно", "headings": [{"tag": "h2", "text": "По радио всем. Мирной делегации в Брест-Литовске особенно", "level": 2, "id": null, "filename": "VL35-G142.html"}]}, {"file": "VL35-G143.html", "title": "Радиограмма Всем, Всем", "headings": [{"tag": "h2", "text": "Радиограмма Всем, Всем", "level": 2, "id": null, "filename": "VL35-G143.html"}]}, {"file": "VL35-G144.html", "title": "Речь перед агитаторами, посылаемыми в провинцию 23 января (5 февраля) 1918 г. Газетный отчет", "headings": [{"tag": "h2", "text": "Речь перед агитаторами, посылаемыми в провинцию 23 января (5 февраля) 1918 г.  Газетный отчет", "level": 2, "id": null, "filename": "VL35-G144.html"}]}, {"file": "VL35-G145.html", "title": "О переводе военных заводов на хозяйственно-полезные работы. \nПроект постановления СНК", "headings": [{"tag": "h2", "text": "О переводе военных заводов на хозяйственно-полезные работы.  Проект постановления СНК", "level": 2, "id": null, "filename": "VL35-G145.html"}]}, {"file": "VL35-G146.html", "title": "Выступления на заседании ЦК РСДРП(б) 24 января (6 февраля) 1918 г. \nПротокольная запись", "headings": [{"tag": "h2", "text": "Выступления на заседании ЦК РСДРП(б) 24 января (6 февраля) 1918 г.    Протокольная запись", "level": 2, "id": "h146-1", "filename": "VL35-G146.html"}, {"tag": "h3", "text": "1", "level": 3, "id": "h146-2", "filename": "VL35-G146.html"}]}, {"file": "VL35-G147.html", "title": "2", "headings": [{"tag": "h3", "text": "2", "level": 3, "id": null, "filename": "VL35-G147.html"}]}, {"file": "VL35-G148.html", "title": "3", "headings": [{"tag": "h3", "text": "3", "level": 3, "id": null, "filename": "VL35-G148.html"}]}, {"file": "VL35-G149.html", "title": "Речь на заседании съезда земельных комитетов и крестьянской секции III съезда Советов 28 января (10 февраля) 1918 г. \nГазетный отчет", "headings": [{"tag": "h2", "text": "Речь на заседании съезда земельных комитетов и крестьянской секции III съезда Советов 28 января (10 февраля) 1918 г.    Газетный отчет", "level": 2, "id": null, "filename": "VL35-G149.html"}]}, {"file": "VL35-G150.html", "title": "Брест-Литовск русская мирная делегация. Троцкому", "headings": [{"tag": "h2", "text": "Брест-Литовск русская мирная делегация. Троцкому  ", "level": 2, "id": null, "filename": "VL35-G150.html"}]}, {"file": "VL35-G151.html", "title": "Постановление СНК о порядке приема на службу саботажников", "headings": [{"tag": "h2", "text": "Постановление СНК о порядке приема на службу саботажников  ", "level": 2, "id": null, "filename": "VL35-G151.html"}]}, {"file": "VL35-G152.html", "title": "Выступления на заседании ЦК РСДРП(б) 18 февраля 1918 г. (утром). Протокольная запись", "headings": [{"tag": "h2", "text": "Выступления на заседании ЦК РСДРП(б) 18 февраля 1918 г. (утром)    .  Протокольная запись", "level": 2, "id": "h152-1", "filename": "VL35-G152.html"}, {"tag": "h3", "text": "1", "level": 3, "id": "h152-2", "filename": "VL35-G152.html"}]}, {"file": "VL35-G153.html", "title": "2", "headings": [{"tag": "h3", "text": "2", "level": 3, "id": null, "filename": "VL35-G153.html"}]}, {"file": "VL35-G154.html", "title": "3", "headings": [{"tag": "h3", "text": "3", "level": 3, "id": null, "filename": "VL35-G154.html"}]}, {"file": "VL35-G155.html", "title": "Речи на заседании ЦК РСДРП(б) 18 февраля 1918 г. (вечером). Протокольная запись", "headings": [{"tag": "h2", "text": "Речи на заседании ЦК РСДРП(б) 18 февраля 1918 г. (вечером)    .  Протокольная запись", "level": 2, "id": "h155-1", "filename": "VL35-G155.html"}, {"tag": "h3", "text": "1", "level": 3, "id": "h155-2", "filename": "VL35-G155.html"}]}, {"file": "VL35-G156.html", "title": "2", "headings": [{"tag": "h3", "text": "2", "level": 3, "id": null, "filename": "VL35-G156.html"}]}, {"file": "VL35-G157.html", "title": "Проект радиограммы правительству Германской империи", "headings": [{"tag": "h2", "text": "Проект радиограммы правительству Германской империи  ", "level": 2, "id": null, "filename": "VL35-G157.html"}]}, {"file": "VL35-G158.html", "title": "Речь на объединенном заседании фракций большевиков и левых эсеров ВЦИК 19 февраля 1918 г. Краткий газетный отчет", "headings": [{"tag": "h2", "text": "Речь на объединенном заседании фракций большевиков и левых эсеров ВЦИК 19 февраля 1918 г.  Краткий газетный отчет", "level": 2, "id": null, "filename": "VL35-G158.html"}]}, {"file": "VL35-G159.html", "title": "Разговор с Московским Советом по прямому проводу 20 февраля 1918 г.", "headings": [{"tag": "h2", "text": "Разговор с Московским Советом по прямому проводу 20 февраля 1918 г.", "level": 2, "id": null, "filename": "VL35-G159.html"}]}, {"file": "VL35-G160.html", "title": "Речь перед Латышскими стрелками 20 февраля 1918 г. Краткий газетный отчет", "headings": [{"tag": "h2", "text": "Речь перед Латышскими стрелками 20 февраля 1918 г.  Краткий газетный отчет", "level": 2, "id": null, "filename": "VL35-G160.html"}]}, {"file": "VL35-G161.html", "title": "О революционной фразе", "headings": [{"tag": "h2", "text": "О революционной фразе  ", "level": 2, "id": null, "filename": "VL35-G161.html"}]}, {"file": "VL35-G162.html", "title": "1", "headings": [{"tag": "h3", "text": "1", "level": 3, "id": null, "filename": "VL35-G162.html"}]}, {"file": "VL35-G163.html", "title": "2", "headings": [{"tag": "h3", "text": "2", "level": 3, "id": null, "filename": "VL35-G163.html"}]}, {"file": "VL35-G164.html", "title": "3", "headings": [{"tag": "h3", "text": "3", "level": 3, "id": null, "filename": "VL35-G164.html"}]}, {"file": "VL35-G165.html", "title": "4", "headings": [{"tag": "h3", "text": "4", "level": 3, "id": null, "filename": "VL35-G165.html"}]}, {"file": "VL35-G166.html", "title": "5", "headings": [{"tag": "h3", "text": "5", "level": 3, "id": null, "filename": "VL35-G166.html"}]}, {"file": "VL35-G167.html", "title": "6", "headings": [{"tag": "h3", "text": "6", "level": 3, "id": null, "filename": "VL35-G167.html"}]}, {"file": "VL35-G168.html", "title": "7", "headings": [{"tag": "h3", "text": "7", "level": 3, "id": null, "filename": "VL35-G168.html"}]}, {"file": "VL35-G169.html", "title": "8", "headings": [{"tag": "h3", "text": "8", "level": 3, "id": null, "filename": "VL35-G169.html"}]}, {"file": "VL35-G170.html", "title": "Телефонограмма в Исполнительную Комиссию Петроградского комитета и во все районные комитеты партии большевиков", "headings": [{"tag": "h2", "text": "Телефонограмма в Исполнительную Комиссию Петроградского комитета и во все районные комитеты партии большевиков  ", "level": 2, "id": null, "filename": "VL35-G170.html"}]}, {"file": "VL35-G171.html", "title": "Социалистическое Отечество в опасности!", "headings": [{"tag": "h2", "text": "Социалистическое Отечество в опасности!  ", "level": 2, "id": null, "filename": "VL35-G171.html"}]}, {"file": "VL35-G172.html", "title": "Дополнение к Декрету СНК «Социалистическое Отечество в опасности!»", "headings": [{"tag": "h2", "text": "Дополнение к Декрету СНК «Социалистическое Отечество в опасности!»", "level": 2, "id": null, "filename": "VL35-G172.html"}]}, {"file": "VL35-G173.html", "title": "О чесотке", "headings": [{"tag": "h2", "text": "О чесотке  ", "level": 2, "id": null, "filename": "VL35-G173.html"}]}, {"file": "VL35-G174.html", "title": "Записка В. Η. Подбельскому в Москву по прямому проводу 22 февраля 1918 г.", "headings": [{"tag": "h2", "text": "Записка В. Η. Подбельскому в Москву по прямому проводу 22 февраля 1918 г.  ", "level": 2, "id": null, "filename": "VL35-G174.html"}]}, {"file": "VL35-G175.html", "title": "Мир или воина?", "headings": [{"tag": "h2", "text": "Мир или воина?", "level": 2, "id": null, "filename": "VL35-G175.html"}]}, {"file": "VL35-G176.html", "title": "Выступления на заседании ЦК РСДРП(б) 23 февраля 1918 г. Протокольная запись", "headings": [{"tag": "h2", "text": "Выступления на заседании ЦК РСДРП(б) 23 февраля 1918 г.    Протокольная запись", "level": 2, "id": "h176-1", "filename": "VL35-G176.html"}, {"tag": "h3", "text": "1", "level": 3, "id": "h176-2", "filename": "VL35-G176.html"}]}, {"file": "VL35-G177.html", "title": "2", "headings": [{"tag": "h3", "text": "2", "level": 3, "id": null, "filename": "VL35-G177.html"}]}, {"file": "VL35-G178.html", "title": "3", "headings": [{"tag": "h3", "text": "3", "level": 3, "id": null, "filename": "VL35-G178.html"}]}, {"file": "VL35-G179.html", "title": "4", "headings": [{"tag": "h3", "text": "4", "level": 3, "id": null, "filename": "VL35-G179.html"}]}, {"file": "VL35-G180.html", "title": "5", "headings": [{"tag": "h3", "text": "5", "level": 3, "id": null, "filename": "VL35-G180.html"}]}, {"file": "VL35-G181.html", "title": "6", "headings": [{"tag": "h3", "text": "6", "level": 3, "id": null, "filename": "VL35-G181.html"}]}, {"file": "VL35-G182.html", "title": "7", "headings": [{"tag": "h3", "text": "7", "level": 3, "id": null, "filename": "VL35-G182.html"}]}, {"file": "VL35-G183.html", "title": "8", "headings": [{"tag": "h3", "text": "8", "level": 3, "id": null, "filename": "VL35-G183.html"}]}, {"file": "VL35-G184.html", "title": "Речь на объединенном заседании фракций большевиков и левых эсеров ВЦИК 23 февраля 1918 г. \nГазетный отчет", "headings": [{"tag": "h2", "text": "Речь на объединенном заседании фракций большевиков и левых эсеров ВЦИК 23 февраля 1918 г.    Газетный отчет", "level": 2, "id": null, "filename": "VL35-G184.html"}]}, {"file": "VL35-G185.html", "title": "В чем ошибка?", "headings": [{"tag": "h2", "text": "В чем ошибка?  ", "level": 2, "id": null, "filename": "VL35-G185.html"}]}, {"file": "VL35-G186.html", "title": "Доклад на заседании ВЦИК \n24 февраля 1918 г.", "headings": [{"tag": "h2", "text": "Доклад на заседании ВЦИК  24 февраля 1918 г.  ", "level": 2, "id": null, "filename": "VL35-G186.html"}]}, {"file": "VL35-G187.html", "title": "Постановление Совета Народных Комиссаров о принятии германских условий мира", "headings": [{"tag": "h2", "text": "Постановление Совета Народных Комиссаров о принятии германских условий мира  ", "level": 2, "id": null, "filename": "VL35-G187.html"}]}, {"file": "VL35-G188.html", "title": "Несчастный мир", "headings": [{"tag": "h2", "text": "Несчастный мир", "level": 2, "id": null, "filename": "VL35-G188.html"}]}, {"file": "VL35-G189.html", "title": "Заметка о необходимости подписать мир", "headings": [{"tag": "h2", "text": "Заметка о необходимости подписать мир", "level": 2, "id": null, "filename": "VL35-G189.html"}]}, {"file": "VL35-G190.html", "title": "Выступления на заседании ЦК РСДРП(б) 24 февраля 1918 г. \nПротокольная запись", "headings": [{"tag": "h2", "text": "Выступления на заседании ЦК РСДРП(б) 24 февраля 1918 г.  Протокольная запись", "level": 2, "id": "h190-1", "filename": "VL35-G190.html"}, {"tag": "h3", "text": "1", "level": 3, "id": "h190-2", "filename": "VL35-G190.html"}]}, {"file": "VL35-G191.html", "title": "2", "headings": [{"tag": "h3", "text": "2", "level": 3, "id": null, "filename": "VL35-G191.html"}]}, {"file": "VL35-G192.html", "title": "3", "headings": [{"tag": "h3", "text": "3", "level": 3, "id": null, "filename": "VL35-G192.html"}]}, {"file": "VL35-G193.html", "title": "4", "headings": [{"tag": "h3", "text": "4", "level": 3, "id": null, "filename": "VL35-G193.html"}]}, {"file": "VL35-G194.html", "title": "5", "headings": [{"tag": "h3", "text": "5", "level": 3, "id": null, "filename": "VL35-G194.html"}]}, {"file": "VL35-G195.html", "title": "6", "headings": [{"tag": "h3", "text": "6", "level": 3, "id": null, "filename": "VL35-G195.html"}]}, {"file": "VL35-G196.html", "title": "7", "headings": [{"tag": "h3", "text": "7", "level": 3, "id": null, "filename": "VL35-G196.html"}]}, {"file": "VL35-G197.html", "title": "8", "headings": [{"tag": "h3", "text": "8", "level": 3, "id": null, "filename": "VL35-G197.html"}]}, {"file": "VL35-G198.html", "title": "9", "headings": [{"tag": "h3", "text": "9", "level": 3, "id": null, "filename": "VL35-G198.html"}]}, {"file": "VL35-G199.html", "title": "10", "headings": [{"tag": "h3", "text": "10", "level": 3, "id": null, "filename": "VL35-G199.html"}]}, {"file": "VL35-G200.html", "title": "11", "headings": [{"tag": "h3", "text": "11", "level": 3, "id": null, "filename": "VL35-G200.html"}]}, {"file": "VL35-G201.html", "title": "Позиция ЦК РСДРП (большевиков) в вопросе о сепаратном и аннексионистском мире", "headings": [{"tag": "h2", "text": "Позиция ЦК РСДРП (большевиков) в вопросе о сепаратном и аннексионистском мире  ", "level": 2, "id": null, "filename": "VL35-G201.html"}]}, {"file": "VL35-G202.html", "title": "Тяжелый, но необходимый урок", "headings": [{"tag": "h2", "text": "Тяжелый, но необходимый урок", "level": 2, "id": null, "filename": "VL35-G202.html"}]}, {"file": "VL35-G203.html", "title": "Проект постановления СНК об эвакуации правительства", "headings": [{"tag": "h2", "text": "Проект постановления СНК об эвакуации правительства  ", "level": 2, "id": null, "filename": "VL35-G203.html"}]}, {"file": "VL35-G204.html", "title": "Странное и чудовищное", "headings": [{"tag": "h2", "text": "Странное и чудовищное", "level": 2, "id": null, "filename": "VL35-G204.html"}]}, {"file": "VL35-G205.html", "title": "На деловую почву", "headings": [{"tag": "h2", "text": "На деловую почву", "level": 2, "id": null, "filename": "VL35-G205.html"}]}, {"file": "VL35-G206.html", "title": "Проект приказа всем Совдепам", "headings": [{"tag": "h2", "text": "Проект приказа всем Совдепам", "level": 2, "id": null, "filename": "VL35-G206.html"}]}, {"file": "VL35-G207.html", "title": "Выступления на заседании Совнаркома 4 марта 1918 г.", "headings": [{"tag": "h2", "text": "Выступления на заседании Совнаркома 4 марта 1918 г.  ", "level": 2, "id": "h207-1", "filename": "VL35-G207.html"}, {"tag": "h3", "text": "1", "level": 3, "id": "h207-2", "filename": "VL35-G207.html"}]}, {"file": "VL35-G208.html", "title": "2", "headings": [{"tag": "h3", "text": "2", "level": 3, "id": null, "filename": "VL35-G208.html"}]}, {"file": "VL35-G209.html", "title": "3", "headings": [{"tag": "h3", "text": "3", "level": 3, "id": null, "filename": "VL35-G209.html"}]}, {"file": "VL35-G210.html", "title": "Серьезный урок и серьезная ответственность", "headings": [{"tag": "h2", "text": "Серьезный урок и серьезная ответственность", "level": 2, "id": null, "filename": "VL35-G210.html"}]}, {"file": "VL35-G211.html", "title": "Подготовительные материалы", "headings": [{"tag": "h1", "text": "Подготовительные материалы", "level": 1, "id": null, "filename": "VL35-G211.html"}, {"tag": "h2", "text": "План речи по аграрному вопросу на чрезвычайном Всероссийском съезде крестьянских депутатов 14 (27) ноября 1917 г.  ", "level": 2, "id": "h211-2", "filename": "VL35-G211.html"}]}, {"file": "VL35-G212.html", "title": "Тезисы о задачах партии + текущий момент", "headings": [{"tag": "h2", "text": "Тезисы о задачах партии + текущий момент", "level": 2, "id": null, "filename": "VL35-G212.html"}]}, {"file": "VL35-G213.html", "title": "План тезисов об Учредительном собрании", "headings": [{"tag": "h2", "text": "План тезисов об Учредительном собрании  ", "level": 2, "id": null, "filename": "VL35-G213.html"}]}, {"file": "VL35-G214.html", "title": "К проекту Декрета о проведении в жизнь национализации банков и о необходимых в связи с этим мерах", "headings": [{"tag": "h2", "text": "К проекту Декрета о проведении в жизнь национализации банков и о необходимых в связи с этим мерах  ", "level": 2, "id": "h214-1", "filename": "VL35-G214.html"}, {"tag": "h3", "text": "1. Набросок проекта декрета  ", "level": 3, "id": "h214-2", "filename": "VL35-G214.html"}]}, {"file": "VL35-G215.html", "title": "2. Тезисы проекта декрета", "headings": [{"tag": "h3", "text": "2. Тезисы проекта декрета", "level": 3, "id": null, "filename": "VL35-G215.html"}]}, {"file": "VL35-G216.html", "title": "Список неразысканных работ В. И. Ленина \n(25 октября (7 ноября) 1917 – 5 марта 1918)", "headings": [{"tag": "h1", "text": "Список неразысканных работ В. И. Ленина  (25 октября (7 ноября) 1917 – 5 марта 1918)", "level": 1, "id": null, "filename": "VL35-G216.html"}, {"tag": "h2", "text": "1917 г.", "level": 2, "id": "h216-2", "filename": "VL35-G216.html"}]}, {"file": "VL35-G217.html", "title": "1918 г.", "headings": [{"tag": "h2", "text": "1918 г.", "level": 2, "id": null, "filename": "VL35-G217.html"}]}, {"file": "VL35-G218.html", "title": "Список документов, в редактировании которых принимал участие В. И. Ленин", "headings": [{"tag": "h1", "text": "Список документов, в редактировании которых принимал участие В. И. Ленин", "level": 1, "id": null, "filename": "VL35-G218.html"}]}, {"file": "VL35-G219.html", "title": "Указатель литературных работ и источников, цитируемых и упоминаемых В. И. Лениным", "headings": [{"tag": "h1", "text": "Указатель литературных работ и источников, цитируемых и упоминаемых В. И. Лениным", "level": 1, "id": null, "filename": "VL35-G219.html"}]}, {"file": "VL35-G220.html", "title": "Указатель имен", "headings": [{"tag": "h1", "text": "Указатель имен", "level": 1, "id": null, "filename": "VL35-G220.html"}]}, {"file": "VL35-G221.html", "title": "Даты жизни и деятельности В. И. Ленина (25 октября (7 ноября) 1917 – 5 марта 1918)", "headings": [{"tag": "h1", "text": "Даты жизни и деятельности В. И. Ленина (25 октября (7 ноября) 1917 – 5 марта 1918)", "level": 1, "id": null, "filename": "VL35-G221.html"}, {"tag": "h2", "text": "1917", "level": 2, "id": "h221-2", "filename": "VL35-G221.html"}]}, {"file": "VL35-G222.html", "title": "1918", "headings": [{"tag": "h2", "text": "1918", "level": 2, "id": null, "filename": "VL35-G222.html"}]}, {"file": "kommentariy.html", "title": "Комментарии - Полное собрание сочинений. Том 35. Октябрь 1917 — март 1918", "headings": [{"tag": "h1", "text": "Комментарии", "level": 1, "id": null, "filename": "kommentariy.html"}]}, {"file": "primechaniya.html", "title": "ПРИМЕЧАНИЯ - Полное собрание сочинений. Том 35. Октябрь 1917 — март 1918", "headings": [{"tag": "h1", "text": "ПРИМЕЧАНИЯ", "level": 1, "id": null, "filename": "primechaniya.html"}]}]